pdm_build_locked-0.3.5.dist-info/METADATA
pdm_build_locked-0.3.5.dist-info/WHEEL
pdm_build_locked-0.3.5.dist-info/entry_points.txt
pdm_build_locked-0.3.5.dist-info/licenses/LICENSE
pdm_build_locked/__init__.py
pdm_build_locked/_utils.py
pdm_build_locked/backend.py
pdm_build_locked/command.py
pdm_build_locked/hatchling.py
pdm_build_locked/plugin.py
pdm_build_locked-0.3.5.dist-info/RECORD
