Metadata-Version: 2.1
Name: pdm-build-locked
Version: 0.3.5
Summary:     pdm-build-locked is a pdm plugin to add locked packages as additional optional dependency groups to the distribution metadata
Keywords: pdm,plugin
Author-Email: sigma67 <sigma67.github@gmail.com>, Frost Ming <me@frostming.com>
Classifier: Topic :: Software Development :: Libraries :: Python Modules
Classifier: Operating System :: OS Independent
Classifier: Programming Language :: Python :: 3
Classifier: Programming Language :: Python :: 3.9
Classifier: Programming Language :: Python :: 3.10
Classifier: Programming Language :: Python :: 3.11
Classifier: Programming Language :: Python :: 3.12
Classifier: Programming Language :: Python :: 3.13
Requires-Python: >=3.9
Requires-Dist: tomli; python_version < "3.11"
